{"replayId":"03e67e4b58a8432da04ce89ea0357c50","startedAt":"2016-08-02T23:12:42.079Z","lastCheckpointTime":1980493,"newCheckpointTime":2040500,"isLive":false,"gameType":"COOP AI","players":[{"team":0,"hero":"HeroData_RiftMage","username":"johnesc","accountId":"0968d7ad261743bb87e3e6bd46d07036","damageToTowers":3150,"damageToHeroes":30824,"damageToJungle":9354,"damageToMinions":52484,"damageToHarvesters":0,"damageToInhibitors":0,"heroLevel":13,"deaths":2,"assists":11,"towerLastHits":0,"mmr":null,"kills":2},{"team":0,"hero":"HeroData_Sword","username":"HaxenFaxen","accountId":"5d34798e28924317aa29ec72957b5110","damageToTowers":2903,"damageToHeroes":4621,"damageToJungle":0,"damageToMinions":34215,"damageToHarvesters":2064,"damageToInhibitors":515,"heroLevel":12,"deaths":8,"assists":1,"towerLastHits":0,"mmr":null,"kills":7},{"team":0,"hero":"HeroData_Venus","username":"MiniFairPlay","accountId":"4fdbfee47f164a1297813315f4c3c90e","damageToTowers":5528,"damageToHeroes":8381,"damageToJungle":0,"damageToMinions":65257,"damageToHarvesters":0,"damageToInhibitors":5262,"heroLevel":10,"deaths":11,"assists":3,"towerLastHits":0,"mmr":null,"kills":4},{"team":0,"hero":"HeroData_HyperBreach","username":"angeltears77","accountId":"8040ed2031e94c7183d45784664c0085","damageToTowers":2898,"damageToHeroes":12342,"damageToJungle":170,"damageToMinions":38436,"damageToHarvesters":0,"damageToInhibitors":997,"heroLevel":14,"deaths":5,"assists":7,"towerLastHits":0,"mmr":null,"kills":3},{"team":0,"hero":"HeroData_Tomahawk","username":"Fragglen","accountId":"22319ceb9bd94a089047d41bd367bfa6","damageToTowers":4780,"damageToHeroes":26695,"damageToJungle":666,"damageToMinions":16754,"damageToHarvesters":2595,"damageToInhibitors":0,"heroLevel":12,"deaths":5,"assists":3,"towerLastHits":0,"mmr":null,"kills":2},{"team":1,"hero":"HeroData_Muriel","username":"Blue_Muriel","accountId":"bot","damageToTowers":0,"damageToHeroes":0,"damageToJungle":0,"damageToMinions":0,"damageToHarvesters":0,"damageToInhibitors":0,"heroLevel":15,"deaths":0,"assists":7,"towerLastHits":1,"mmr":null,"kills":11},{"team":1,"hero":"HeroData_Price","username":"Blue_Murdock","accountId":"bot","damageToTowers":0,"damageToHeroes":0,"damageToJungle":0,"damageToMinions":0,"damageToHarvesters":0,"damageToInhibitors":0,"heroLevel":13,"deaths":1,"assists":2,"towerLastHits":2,"mmr":null,"kills":4},{"team":1,"hero":"HeroData_ArcBlade","username":"Blue_Feng Mao","accountId":"bot","damageToTowers":0,"damageToHeroes":0,"damageToJungle":0,"damageToMinions":0,"damageToHarvesters":0,"damageToInhibitors":0,"heroLevel":12,"deaths":2,"assists":3,"towerLastHits":2,"mmr":null,"kills":1},{"team":1,"hero":"HeroData_Totem","username":"Blue_Dekker","accountId":"bot","damageToTowers":0,"damageToHeroes":0,"damageToJungle":0,"damageToMinions":0,"damageToHarvesters":0,"damageToInhibitors":0,"heroLevel":12,"deaths":10,"assists":7,"towerLastHits":0,"mmr":null,"kills":0},{"team":1,"hero":"HeroData_Rampage","username":"Blue_Rampage","accountId":"bot","damageToTowers":0,"damageToHeroes":0,"damageToJungle":0,"damageToMinions":0,"damageToHarvesters":0,"damageToInhibitors":0,"heroLevel":13,"deaths":7,"assists":2,"towerLastHits":1,"mmr":null,"kills":15}],"kills":[{"killer":"Fragglen","killed":"Blue_Feng Mao","timestamp":103741},{"killer":"johnesc","killed":"Blue_Rampage","timestamp":151371},{"killer":"Blue_Dekker","killed":"HaxenFaxen","timestamp":210241},{"killer":"Blue_Dekker","killed":"MiniFairPlay","timestamp":211347},{"killer":"johnesc","killed":"Blue_Rampage","timestamp":223195},{"killer":"Fragglen","killed":"Blue_Murdock","timestamp":240077},{"killer":"Fragglen","killed":"Blue_Dekker","timestamp":273408},{"killer":"Blue_Murdock","killed":"Fragglen","timestamp":326624},{"killer":"johnesc","killed":"Blue_Murdock","timestamp":335364},{"killer":"Blue_Murdock","killed":"Fragglen","timestamp":326624},{"killer":"johnesc","killed":"Blue_Murdock","timestamp":335364},{"killer":"johnesc","killed":"Blue_Feng Mao","timestamp":378386},{"killer":"johnesc","killed":"Blue_Feng Mao","timestamp":378386},{"killer":"Blue_Rampage","killed":"Fragglen","timestamp":495066},{"killer":"johnesc","killed":"Blue_Feng Mao","timestamp":504838},{"killer":"Blue_Rampage","killed":"Fragglen","timestamp":495066},{"killer":"johnesc","killed":"Blue_Feng Mao","timestamp":504838},{"killer":"Blue_Rampage","killed":"angeltears77","timestamp":558889},{"killer":"Blue_Rampage","killed":"angeltears77","timestamp":558889},{"killer":"Fragglen","killed":"Blue_Dekker","timestamp":619221},{"killer":"Fragglen","killed":"Blue_Muriel","timestamp":649970},{"killer":"Fragglen","killed":"Blue_Dekker","timestamp":619221},{"killer":"Fragglen","killed":"Blue_Muriel","timestamp":649970},{"killer":"Fragglen","killed":"Blue_Dekker","timestamp":619221},{"killer":"Fragglen","killed":"Blue_Muriel","timestamp":649970},{"killer":"Blue_Muriel","killed":"angeltears77","timestamp":914232},{"killer":"johnesc","killed":"Blue_Murdock","timestamp":927279},{"killer":"Blue_Muriel","killed":"angeltears77","timestamp":914232},{"killer":"johnesc","killed":"Blue_Murdock","timestamp":927279},{"killer":"Fragglen","killed":"Blue_Feng Mao","timestamp":981398},{"killer":"HaxenFaxen","killed":"Blue_Murdock","timestamp":1009834},{"killer":"HaxenFaxen","killed":"Blue_Dekker","timestamp":1040895},{"killer":"HaxenFaxen","killed":"Blue_Feng Mao","timestamp":1066650},{"killer":"johnesc","killed":"Blue_Muriel","timestamp":1233696},{"killer":"Fragglen","killed":"Blue_Feng Mao","timestamp":1268238},{"killer":"HaxenFaxen","killed":"Blue_Murdock","timestamp":1296303},{"killer":"Blue_Dekker","killed":"angeltears77","timestamp":1298043},{"killer":"Fragglen","killed":"Blue_Feng Mao","timestamp":1268238},{"killer":"HaxenFaxen","killed":"Blue_Murdock","timestamp":1296303},{"killer":"Blue_Dekker","killed":"angeltears77","timestamp":1298043},{"killer":"Fragglen","killed":"Blue_Feng Mao","timestamp":1362962},{"killer":"johnesc","killed":"Blue_Murdock","timestamp":1369419},{"killer":"Fragglen","killed":"Blue_Feng Mao","timestamp":1421942},{"killer":"Blue_Murdock","killed":"angeltears77","timestamp":1444740},{"killer":"Blue_Murdock","killed":"MiniFairPlay","timestamp":1457552},{"killer":"Blue_Murdock","killed":"angeltears77","timestamp":1444740},{"killer":"Blue_Murdock","killed":"MiniFairPlay","timestamp":1457552},{"killer":"Blue_Feng Mao","killed":"Fragglen","timestamp":1512623},{"killer":"Fragglen","killed":"Blue_Dekker","timestamp":1607502},{"killer":"Fragglen","killed":"Blue_Rampage","timestamp":1662875},{"killer":"Blue_Murdock","killed":"angeltears77","timestamp":1663979},{"killer":"Fragglen","killed":"Blue_Rampage","timestamp":1662875},{"killer":"Blue_Murdock","killed":"angeltears77","timestamp":1663979},{"killer":"Blue_Feng Mao","killed":"Fragglen","timestamp":1692335},{"killer":"johnesc","killed":"Blue_Feng Mao","timestamp":1702505},{"killer":"Fragglen","killed":"Blue_Feng Mao","timestamp":1812230},{"killer":"Fragglen","killed":"Blue_Rampage","timestamp":1831879},{"killer":"MiniFairPlay","killed":"Blue_Murdock","timestamp":1838635},{"killer":"Blue_Feng Mao","killed":"angeltears77","timestamp":1875410},{"killer":"Blue_Muriel","killed":"Fragglen","timestamp":1896619},{"killer":"Blue_Feng Mao","killed":"angeltears77","timestamp":1875410},{"killer":"Blue_Muriel","killed":"Fragglen","timestamp":1896619},{"killer":"johnesc","killed":"Blue_Feng Mao","timestamp":1977416},{"killer":"Blue_Murdock","killed":"angeltears77","timestamp":1997110},{"killer":"johnesc","killed":"Blue_Rampage","timestamp":2013976}],"towerKills":[{"killer":"johnesc","timestamp":427790},{"killer":"johnesc","timestamp":427790},{"killer":"Fragglen","timestamp":1215901},{"killer":"HaxenFaxen","timestamp":1361825},{"killer":"johnesc","timestamp":1393509},{"killer":"MiniFairPlay","timestamp":1601849},{"killer":"MiniFairPlay","timestamp":1736963},{"killer":"MiniFairPlay","timestamp":1880192},{"killer":"MiniFairPlay","timestamp":1880192},{"killer":"MiniFairPlay","timestamp":2013742}],"winningTeam":0}