{"replayId":"1eb0f6d6ac2e40388decb573702a31ea","startedAt":"2016-08-03T21:27:41.976Z","lastCheckpointTime":840223,"newCheckpointTime":900253,"isLive":false,"gameType":"SOLO AI","players":[{"team":0,"hero":"HeroData_Sword","username":"GrahamKrackers","accountId":"1464738792fd4c2e8891b4fe24746a13","damageToTowers":396,"damageToHeroes":428,"damageToJungle":0,"damageToMinions":4707,"damageToHarvesters":0,"damageToInhibitors":0,"heroLevel":15,"deaths":1,"assists":18,"towerLastHits":1,"mmr":null,"kills":17},{"team":0,"hero":"HeroData_TwinBlast","username":"Red_TwinBlast","accountId":"bot","damageToTowers":0,"damageToHeroes":0,"damageToJungle":0,"damageToMinions":0,"damageToHarvesters":0,"damageToInhibitors":0,"heroLevel":15,"deaths":0,"assists":16,"towerLastHits":1,"mmr":null,"kills":21},{"team":0,"hero":"HeroData_Sparrow","username":"Red_Sparrow","accountId":"bot","damageToTowers":0,"damageToHeroes":0,"damageToJungle":0,"damageToMinions":0,"damageToHarvesters":0,"damageToInhibitors":0,"heroLevel":14,"deaths":4,"assists":4,"towerLastHits":1,"mmr":null,"kills":10},{"team":0,"hero":"HeroData_Rampage","username":"Red_Rampage","accountId":"bot","damageToTowers":0,"damageToHeroes":0,"damageToJungle":0,"damageToMinions":0,"damageToHarvesters":0,"damageToInhibitors":0,"heroLevel":15,"deaths":0,"assists":13,"towerLastHits":1,"mmr":null,"kills":30},{"team":0,"hero":"HeroData_HyperBreach","username":"Red_Howitzer","accountId":"bot","damageToTowers":0,"damageToHeroes":0,"damageToJungle":0,"damageToMinions":0,"damageToHarvesters":0,"damageToInhibitors":0,"heroLevel":9,"deaths":24,"assists":0,"towerLastHits":0,"mmr":null,"kills":1},{"team":1,"hero":"HeroData_Kurohane","username":"Blue_Kallari","accountId":"bot","damageToTowers":0,"damageToHeroes":0,"damageToJungle":0,"damageToMinions":0,"damageToHarvesters":0,"damageToInhibitors":0,"heroLevel":11,"deaths":17,"assists":1,"towerLastHits":0,"mmr":null,"kills":1},{"team":1,"hero":"HeroData_RiftMage","username":"Blue_Gideon","accountId":"bot","damageToTowers":0,"damageToHeroes":0,"damageToJungle":0,"damageToMinions":0,"damageToHarvesters":0,"damageToInhibitors":0,"heroLevel":10,"deaths":24,"assists":1,"towerLastHits":0,"mmr":null,"kills":1},{"team":1,"hero":"HeroData_ArcBlade","username":"Blue_Feng Mao","accountId":"bot","damageToTowers":0,"damageToHeroes":0,"damageToJungle":0,"damageToMinions":0,"damageToHarvesters":0,"damageToInhibitors":0,"heroLevel":13,"deaths":13,"assists":1,"towerLastHits":0,"mmr":null,"kills":1},{"team":1,"hero":"HeroData_Totem","username":"Blue_Dekker","accountId":"bot","damageToTowers":0,"damageToHeroes":0,"damageToJungle":0,"damageToMinions":0,"damageToHarvesters":0,"damageToInhibitors":0,"heroLevel":11,"deaths":14,"assists":1,"towerLastHits":0,"mmr":null,"kills":0},{"team":1,"hero":"HeroData_Muriel","username":"Blue_Muriel","accountId":"bot","damageToTowers":0,"damageToHeroes":0,"damageToJungle":0,"damageToMinions":0,"damageToHarvesters":0,"damageToInhibitors":0,"heroLevel":15,"deaths":0,"assists":12,"towerLastHits":1,"mmr":null,"kills":11}],"kills":[{"killer":"Red_TwinBlast","killed":"Blue_Kallari","timestamp":87752},{"killer":"GrahamKrackers","killed":"Blue_Feng Mao","timestamp":99330},{"killer":"Red_Howitzer","killed":"Blue_Dekker","timestamp":197922},{"killer":"Red_Sparrow","killed":"Blue_Muriel","timestamp":199762},{"killer":"Red_Rampage","killed":"Blue_Kallari","timestamp":216226},{"killer":"Red_Howitzer","killed":"Blue_Feng Mao","timestamp":222518},{"killer":"Blue_Gideon","killed":"Red_Rampage","timestamp":284753},{"killer":"Red_Howitzer","killed":"Blue_Kallari","timestamp":308864},{"killer":"Red_TwinBlast","killed":"Blue_Gideon","timestamp":316928},{"killer":"Red_Howitzer","killed":"Blue_Feng Mao","timestamp":334431},{"killer":"Red_Howitzer","killed":"Blue_Dekker","timestamp":426441},{"killer":"Red_Howitzer","killed":"Blue_Kallari","timestamp":449368},{"killer":"Red_Rampage","killed":"Blue_Feng Mao","timestamp":455995},{"killer":"GrahamKrackers","killed":"Blue_Feng Mao","timestamp":538817},{"killer":"Blue_Feng Mao","killed":"Red_Rampage","timestamp":632475},{"killer":"Red_Howitzer","killed":"Blue_Muriel","timestamp":661715},{"killer":"Red_Sparrow","killed":"Blue_Gideon","timestamp":671088},{"killer":"Red_Sparrow","killed":"Blue_Feng Mao","timestamp":715839},{"killer":"Red_Howitzer","killed":"Blue_Dekker","timestamp":765092},{"killer":"Red_TwinBlast","killed":"Blue_Gideon","timestamp":791276},{"killer":"Red_Sparrow","killed":"Blue_Muriel","timestamp":816210},{"killer":"Red_Rampage","killed":"Blue_Kallari","timestamp":831222},{"killer":"Red_Sparrow","killed":"Blue_Gideon","timestamp":880796},{"killer":"Red_TwinBlast","killed":"Blue_Feng Mao","timestamp":880897}],"towerKills":[],"winningTeam":null}