{"replayId":"748dcda6d7a34fc1bf7d13a70e4839a8","startedAt":"2016-08-03T22:01:22.381Z","lastCheckpointTime":1680495,"newCheckpointTime":1740519,"isLive":false,"gameType":"PVP","players":[{"team":0,"hero":"HeroData_Tomahawk","username":"uttaka","accountId":"c060d4144f014edf9e4db19c5c1c7a44","damageToTowers":0,"damageToHeroes":4836,"damageToJungle":0,"damageToMinions":3818,"damageToHarvesters":0,"damageToInhibitors":0,"heroLevel":8,"deaths":6,"assists":0,"towerLastHits":0,"mmr":null,"kills":5},{"team":1,"hero":"HeroData_RiftMage","username":"blazejanpanashe","accountId":"69b5f5394ef14a859cf3e5ebc84c1db2","damageToTowers":2475,"damageToHeroes":3596,"damageToJungle":0,"damageToMinions":27866,"damageToHarvesters":0,"damageToInhibitors":2051,"heroLevel":11,"deaths":1,"assists":3,"towerLastHits":1,"mmr":null,"kills":3},{"team":0,"hero":"HeroData_Totem","username":"AlexSao16","accountId":"f6422bfa193743988588a4d0bd77a02d","damageToTowers":180,"damageToHeroes":2316,"damageToJungle":0,"damageToMinions":7517,"damageToHarvesters":0,"damageToInhibitors":0,"heroLevel":9,"deaths":6,"assists":1,"towerLastHits":0,"mmr":null,"kills":1},{"team":1,"hero":"HeroData_Grux","username":"TheExpertKillr21","accountId":"6b4866cbf9c74f7ab21d878373b7df87","damageToTowers":101,"damageToHeroes":4158,"damageToJungle":0,"damageToMinions":13296,"damageToHarvesters":0,"damageToInhibitors":661,"heroLevel":9,"deaths":7,"assists":1,"towerLastHits":0,"mmr":null,"kills":3},{"team":0,"hero":"HeroData_Grux","username":"Caicia","accountId":"3d69ee7ca7384024a4cace449b97875e","damageToTowers":0,"damageToHeroes":8547,"damageToJungle":0,"damageToMinions":26716,"damageToHarvesters":65,"damageToInhibitors":0,"heroLevel":12,"deaths":2,"assists":1,"towerLastHits":0,"mmr":null,"kills":4},{"team":1,"hero":"HeroData_Sword","username":"TheSchrute","accountId":"e69516a6023c47238901385ca9c8faac","damageToTowers":749,"damageToHeroes":8567,"damageToJungle":6712,"damageToMinions":16674,"damageToHarvesters":0,"damageToInhibitors":495,"heroLevel":13,"deaths":0,"assists":5,"towerLastHits":0,"mmr":null,"kills":10},{"team":1,"hero":"HeroData_Gadget","username":"Frookie","accountId":"cb52e349c4964acf9de3fe690cb22b3e","damageToTowers":3716,"damageToHeroes":8366,"damageToJungle":0,"damageToMinions":49515,"damageToHarvesters":0,"damageToInhibitors":3111,"heroLevel":14,"deaths":1,"assists":7,"towerLastHits":4,"mmr":null,"kills":6},{"team":0,"hero":"HeroData_Sparrow","username":"Gothphantom","accountId":"878700a9707b4e0c8c6c872b3c573ae3","damageToTowers":87,"damageToHeroes":4224,"damageToJungle":0,"damageToMinions":24264,"damageToHarvesters":0,"damageToInhibitors":0,"heroLevel":11,"deaths":5,"assists":1,"towerLastHits":0,"mmr":null,"kills":1},{"team":1,"hero":"HeroData_Sparrow","username":"HeatIslandEffect","accountId":"9d647d4110fa47dbaa94546ee062b330","damageToTowers":2731,"damageToHeroes":3302,"damageToJungle":0,"damageToMinions":27064,"damageToHarvesters":3059,"damageToInhibitors":1763,"heroLevel":11,"deaths":2,"assists":2,"towerLastHits":1,"mmr":null,"kills":3},{"team":0,"hero":"HeroData_Price","username":"Curtaxew","accountId":"3c01bea1a1d145b6a251b7b9b9f86214","damageToTowers":0,"damageToHeroes":3167,"damageToJungle":1943,"damageToMinions":3742,"damageToHarvesters":0,"damageToInhibitors":0,"heroLevel":7,"deaths":7,"assists":3,"towerLastHits":0,"mmr":null,"kills":0}],"kills":[{"killer":"AlexSao16","killed":"TheExpertKillr21","timestamp":130557},{"killer":"uttaka","killed":"TheExpertKillr21","timestamp":231154},{"killer":"HeatIslandEffect","killed":"uttaka","timestamp":232468},{"killer":"TheSchrute","killed":"Gothphantom","timestamp":270398},{"killer":"Frookie","killed":"Curtaxew","timestamp":284960},{"killer":"TheSchrute","killed":"Curtaxew","timestamp":368566},{"killer":"HeatIslandEffect","killed":"uttaka","timestamp":392934},{"killer":"uttaka","killed":"blazejanpanashe","timestamp":392968},{"killer":"TheExpertKillr21","killed":"AlexSao16","timestamp":400391},{"killer":"uttaka","killed":"HeatIslandEffect","timestamp":623234},{"killer":"Frookie","killed":"uttaka","timestamp":637222},{"killer":"blazejanpanashe","killed":"Curtaxew","timestamp":653638},{"killer":"TheSchrute","killed":"Caicia","timestamp":665545},{"killer":"uttaka","killed":"TheExpertKillr21","timestamp":716608},{"killer":"blazejanpanashe","killed":"uttaka","timestamp":749742},{"killer":"TheSchrute","killed":"AlexSao16","timestamp":762208},{"killer":"Frookie","killed":"Curtaxew","timestamp":771589},{"killer":"uttaka","killed":"TheExpertKillr21","timestamp":821744},{"killer":"Frookie","killed":"uttaka","timestamp":841526},{"killer":"Caicia","killed":"Frookie","timestamp":860564},{"killer":"TheSchrute","killed":"Curtaxew","timestamp":946364},{"killer":"Frookie","killed":"Gothphantom","timestamp":951685},{"killer":"TheSchrute","killed":"AlexSao16","timestamp":957572},{"killer":"TheSchrute","killed":"uttaka","timestamp":1039046},{"killer":"TheExpertKillr21","killed":"Curtaxew","timestamp":1055248},{"killer":"TheExpertKillr21","killed":"Gothphantom","timestamp":1066212},{"killer":"Caicia","killed":"HeatIslandEffect","timestamp":1228642},{"killer":"Gothphantom","killed":"TheExpertKillr21","timestamp":1229652},{"killer":"blazejanpanashe","killed":"AlexSao16","timestamp":1362834},{"killer":"Caicia","killed":"TheExpertKillr21","timestamp":1446498},{"killer":"TheSchrute","killed":"Gothphantom","timestamp":1464597},{"killer":"Frookie","killed":"AlexSao16","timestamp":1471988},{"killer":"Caicia","killed":"TheExpertKillr21","timestamp":1624592},{"killer":"HeatIslandEffect","killed":"Caicia","timestamp":1735378}],"towerKills":[{"killer":"Frookie","timestamp":524237},{"killer":"Frookie","timestamp":594013},{"killer":"blazejanpanashe","timestamp":903015},{"killer":"Frookie","timestamp":1089423},{"killer":"Frookie","timestamp":1275212},{"killer":"HeatIslandEffect","timestamp":1409338},{"killer":"HeatIslandEffect","timestamp":1615256},{"killer":"TheSchrute","timestamp":1662395},{"killer":"blazejanpanashe","timestamp":1684640}],"winningTeam":1}