{"replayId":"9a2650348b9f4f76b457fb8b01692ed6","startedAt":"2016-08-04T15:36:37.383Z","lastCheckpointTime":1860596,"newCheckpointTime":1920618,"isLive":false,"gameType":"PVP","players":[{"team":1,"hero":"HeroData_Venus","username":"xX_BLiNd23_Xx","accountId":"154386ae93234423b6c40c433010aa89","damageToTowers":597,"damageToHeroes":8036,"damageToJungle":0,"damageToMinions":25290,"damageToHarvesters":0,"damageToInhibitors":0,"heroLevel":12,"deaths":3,"assists":2,"towerLastHits":1,"mmr":null,"kills":4},{"team":0,"hero":"HeroData_ArcBlade","username":"tylerk124","accountId":"88412e0e0cdc40288aba3f5383daf193","damageToTowers":2729,"damageToHeroes":11959,"damageToJungle":3411,"damageToMinions":22240,"damageToHarvesters":3325,"damageToInhibitors":1535,"heroLevel":12,"deaths":2,"assists":0,"towerLastHits":2,"mmr":null,"kills":10},{"team":1,"hero":"HeroData_Gadget","username":"z-ReY---","accountId":"d30448528e61423a87bc04863a97fc5d","damageToTowers":0,"damageToHeroes":9052,"damageToJungle":7820,"damageToMinions":9946,"damageToHarvesters":0,"damageToInhibitors":0,"heroLevel":12,"deaths":1,"assists":4,"towerLastHits":0,"mmr":null,"kills":4},{"team":0,"hero":"HeroData_Price","username":"blausio","accountId":"d13536cc5f514d099ce1a26160611e41","damageToTowers":1543,"damageToHeroes":2544,"damageToJungle":53,"damageToMinions":14224,"damageToHarvesters":0,"damageToInhibitors":819,"heroLevel":10,"deaths":4,"assists":2,"towerLastHits":2,"mmr":null,"kills":1},{"team":1,"hero":"HeroData_RiftMage","username":"dturner1203","accountId":"40ed222b996a42ac88b8b285fcd9dba7","damageToTowers":429,"damageToHeroes":7072,"damageToJungle":7395,"damageToMinions":16904,"damageToHarvesters":0,"damageToInhibitors":0,"heroLevel":11,"deaths":7,"assists":1,"towerLastHits":0,"mmr":null,"kills":4},{"team":0,"hero":"HeroData_Kurohane","username":"Kaleb240","accountId":"57a096273278468493ce9b2d2eefb693","damageToTowers":1899,"damageToHeroes":5666,"damageToJungle":4141,"damageToMinions":16136,"damageToHarvesters":2216,"damageToInhibitors":555,"heroLevel":11,"deaths":6,"assists":4,"towerLastHits":1,"mmr":null,"kills":3},{"team":0,"hero":"HeroData_RiftMage","username":"PatoBodo","accountId":"64d02c8e2f7d4824ac8ceb3cc5ad68ee","damageToTowers":3108,"damageToHeroes":4522,"damageToJungle":0,"damageToMinions":45436,"damageToHarvesters":0,"damageToInhibitors":1544,"heroLevel":11,"deaths":2,"assists":1,"towerLastHits":1,"mmr":null,"kills":4},{"team":0,"hero":"HeroData_HyperBreach","username":"phantomcrash187","accountId":"3ff69dddf0924b49a67e4b2de1f9ca1c","damageToTowers":946,"damageToHeroes":3762,"damageToJungle":0,"damageToMinions":25600,"damageToHarvesters":594,"damageToInhibitors":624,"heroLevel":11,"deaths":5,"assists":5,"towerLastHits":0,"mmr":null,"kills":0},{"team":1,"hero":"HeroData_Totem","username":"psychtrip86","accountId":"a958aa24b0a44b5e962eba48d4139fae","damageToTowers":479,"damageToHeroes":1622,"damageToJungle":495,"damageToMinions":2034,"damageToHarvesters":0,"damageToInhibitors":0,"heroLevel":5,"deaths":5,"assists":0,"towerLastHits":0,"mmr":null,"kills":0},{"team":1,"hero":"HeroData_Kurohane","username":"turnerclay681","accountId":"df0917ca65864512b07fe6e6f375aa13","damageToTowers":65,"damageToHeroes":1431,"damageToJungle":1384,"damageToMinions":12671,"damageToHarvesters":0,"damageToInhibitors":0,"heroLevel":10,"deaths":8,"assists":1,"towerLastHits":0,"mmr":null,"kills":1}],"kills":[{"killer":"xX_BLiNd23_Xx","killed":"tylerk124","timestamp":129105},{"killer":"PatoBodo","killed":"psychtrip86","timestamp":154069},{"killer":"tylerk124","killed":"psychtrip86","timestamp":260420},{"killer":"tylerk124","killed":"psychtrip86","timestamp":439965},{"killer":"PatoBodo","killed":"turnerclay681","timestamp":464866},{"killer":"tylerk124","killed":"turnerclay681","timestamp":528748},{"killer":"tylerk124","killed":"dturner1203","timestamp":611234},{"killer":"tylerk124","killed":"psychtrip86","timestamp":670780},{"killer":"dturner1203","killed":"Kaleb240","timestamp":691959},{"killer":"blausio","killed":"dturner1203","timestamp":694547},{"killer":"dturner1203","killed":"phantomcrash187","timestamp":850785},{"killer":"PatoBodo","killed":"dturner1203","timestamp":943654},{"killer":"dturner1203","killed":"blausio","timestamp":945196},{"killer":"z-ReY---","killed":"phantomcrash187","timestamp":986897},{"killer":"Kaleb240","killed":"turnerclay681","timestamp":1016774},{"killer":"tylerk124","killed":"dturner1203","timestamp":1137164},{"killer":"xX_BLiNd23_Xx","killed":"tylerk124","timestamp":1147839},{"killer":"z-ReY---","killed":"phantomcrash187","timestamp":1167908},{"killer":"tylerk124","killed":"xX_BLiNd23_Xx","timestamp":1224502},{"killer":"PatoBodo","killed":"z-ReY---","timestamp":1230865},{"killer":"tylerk124","killed":"turnerclay681","timestamp":1296118},{"killer":"xX_BLiNd23_Xx","killed":"PatoBodo","timestamp":1347118},{"killer":"dturner1203","killed":"blausio","timestamp":1423796},{"killer":"tylerk124","killed":"dturner1203","timestamp":1440669},{"killer":"xX_BLiNd23_Xx","killed":"blausio","timestamp":1527266},{"killer":"turnerclay681","killed":"PatoBodo","timestamp":1537125},{"killer":"Kaleb240","killed":"xX_BLiNd23_Xx","timestamp":1544817},{"killer":"z-ReY---","killed":"phantomcrash187","timestamp":1552610},{"killer":"Kaleb240","killed":"turnerclay681","timestamp":1564741},{"killer":"tylerk124","killed":"dturner1203","timestamp":1604897},{"killer":"z-ReY---","killed":"Kaleb240","timestamp":1704114}],"towerKills":[{"killer":"PatoBodo","timestamp":511954},{"killer":"xX_BLiNd23_Xx","timestamp":566662},{"killer":"tylerk124","timestamp":750920},{"killer":"tylerk124","timestamp":974956},{"killer":"Kaleb240","timestamp":1091735},{"killer":"blausio","timestamp":1165801},{"killer":"blausio","timestamp":1707927},{"killer":"blausio","timestamp":1773881}],"winningTeam":0}