{"replayId":"ab903af5eb1f4532adf6fa2d3518b930","startedAt":"2016-08-04T15:29:36.230Z","lastCheckpointTime":2040504,"newCheckpointTime":2100505,"isLive":false,"gameType":"SOLO AI","players":[{"team":0,"hero":"HeroData_RiftMage","username":"jcalvin95","accountId":"be0800cade594eb5b55c9b24db373d68","damageToTowers":1686,"damageToHeroes":17139,"damageToJungle":2932,"damageToMinions":54519,"damageToHarvesters":0,"damageToInhibitors":3084,"heroLevel":15,"deaths":0,"assists":7,"towerLastHits":0,"mmr":null,"kills":24},{"team":0,"hero":"HeroData_Sparrow","username":"Red_Sparrow","accountId":"bot","damageToTowers":0,"damageToHeroes":0,"damageToJungle":0,"damageToMinions":0,"damageToHarvesters":0,"damageToInhibitors":0,"heroLevel":13,"deaths":2,"assists":9,"towerLastHits":0,"mmr":null,"kills":4},{"team":0,"hero":"HeroData_Rampage","username":"Red_Rampage","accountId":"bot","damageToTowers":0,"damageToHeroes":0,"damageToJungle":0,"damageToMinions":0,"damageToHarvesters":0,"damageToInhibitors":0,"heroLevel":15,"deaths":1,"assists":11,"towerLastHits":1,"mmr":null,"kills":21},{"team":0,"hero":"HeroData_Price","username":"Red_Murdock","accountId":"bot","damageToTowers":0,"damageToHeroes":0,"damageToJungle":0,"damageToMinions":0,"damageToHarvesters":0,"damageToInhibitors":0,"heroLevel":15,"deaths":3,"assists":16,"towerLastHits":1,"mmr":null,"kills":13},{"team":0,"hero":"HeroData_TwinBlast","username":"Red_TwinBlast","accountId":"bot","damageToTowers":0,"damageToHeroes":0,"damageToJungle":0,"damageToMinions":0,"damageToHarvesters":0,"damageToInhibitors":0,"heroLevel":12,"deaths":16,"assists":3,"towerLastHits":0,"mmr":null,"kills":2},{"team":1,"hero":"HeroData_HyperBreach","username":"Blue_Howitzer","accountId":"bot","damageToTowers":0,"damageToHeroes":0,"damageToJungle":0,"damageToMinions":0,"damageToHarvesters":0,"damageToInhibitors":0,"heroLevel":9,"deaths":21,"assists":2,"towerLastHits":0,"mmr":null,"kills":0},{"team":1,"hero":"HeroData_Kurohane","username":"Blue_Kallari","accountId":"bot","damageToTowers":0,"damageToHeroes":0,"damageToJungle":0,"damageToMinions":0,"damageToHarvesters":0,"damageToInhibitors":0,"heroLevel":11,"deaths":17,"assists":1,"towerLastHits":0,"mmr":null,"kills":2},{"team":1,"hero":"HeroData_Muriel","username":"Blue_Muriel","accountId":"bot","damageToTowers":0,"damageToHeroes":0,"damageToJungle":0,"damageToMinions":0,"damageToHarvesters":0,"damageToInhibitors":0,"heroLevel":13,"deaths":12,"assists":2,"towerLastHits":0,"mmr":null,"kills":1},{"team":1,"hero":"HeroData_Gadget","username":"Blue_Gadget","accountId":"bot","damageToTowers":0,"damageToHeroes":0,"damageToJungle":0,"damageToMinions":0,"damageToHarvesters":0,"damageToInhibitors":0,"heroLevel":10,"deaths":24,"assists":1,"towerLastHits":0,"mmr":null,"kills":3},{"team":1,"hero":"HeroData_Steel","username":"Blue_Steel","accountId":"bot","damageToTowers":0,"damageToHeroes":0,"damageToJungle":0,"damageToMinions":0,"damageToHarvesters":0,"damageToInhibitors":0,"heroLevel":15,"deaths":2,"assists":16,"towerLastHits":1,"mmr":null,"kills":25}],"kills":[{"killer":"Red_Murdock","killed":"Blue_Steel","timestamp":78838},{"killer":"Red_Murdock","killed":"Blue_Kallari","timestamp":89082},{"killer":"Red_Murdock","killed":"Blue_Steel","timestamp":158113},{"killer":"Red_Rampage","killed":"Blue_Kallari","timestamp":188995},{"killer":"Red_Murdock","killed":"Blue_Gadget","timestamp":212424},{"killer":"Red_TwinBlast","killed":"Blue_Muriel","timestamp":215470},{"killer":"Red_Sparrow","killed":"Blue_Steel","timestamp":230563},{"killer":"Red_Rampage","killed":"Blue_Kallari","timestamp":254073},{"killer":"Red_TwinBlast","killed":"Blue_Howitzer","timestamp":263546},{"killer":"jcalvin95","killed":"Blue_Steel","timestamp":315565},{"killer":"Red_Sparrow","killed":"Blue_Kallari","timestamp":335341},{"killer":"Red_Sparrow","killed":"Blue_Muriel","timestamp":462406},{"killer":"Red_Murdock","killed":"Blue_Howitzer","timestamp":469536},{"killer":"jcalvin95","killed":"Blue_Gadget","timestamp":473518},{"killer":"Red_Sparrow","killed":"Blue_Kallari","timestamp":489101},{"killer":"Red_Rampage","killed":"Blue_Steel","timestamp":506404},{"killer":"Red_Sparrow","killed":"Blue_Kallari","timestamp":553232},{"killer":"Red_Sparrow","killed":"Blue_Muriel","timestamp":577524},{"killer":"Red_Sparrow","killed":"Blue_Steel","timestamp":594436},{"killer":"Red_Murdock","killed":"Blue_Howitzer","timestamp":636282},{"killer":"jcalvin95","killed":"Blue_Muriel","timestamp":686175},{"killer":"Red_Murdock","killed":"Blue_Kallari","timestamp":695042},{"killer":"Red_Sparrow","killed":"Blue_Steel","timestamp":701484},{"killer":"jcalvin95","killed":"Blue_Howitzer","timestamp":752638},{"killer":"Red_TwinBlast","killed":"Blue_Muriel","timestamp":790529},{"killer":"Red_Sparrow","killed":"Blue_Steel","timestamp":833112},{"killer":"Red_Sparrow","killed":"Blue_Kallari","timestamp":872559},{"killer":"Blue_Howitzer","killed":"Red_TwinBlast","timestamp":891111},{"killer":"Red_Murdock","killed":"Blue_Howitzer","timestamp":916427},{"killer":"Red_Murdock","killed":"Blue_Gadget","timestamp":938284},{"killer":"jcalvin95","killed":"Blue_Steel","timestamp":938652},{"killer":"jcalvin95","killed":"Blue_Kallari","timestamp":948138},{"killer":"Red_Murdock","killed":"Blue_Muriel","timestamp":949309},{"killer":"Blue_Steel","killed":"Red_Murdock","timestamp":1006835},{"killer":"Red_TwinBlast","killed":"Blue_Steel","timestamp":1011855},{"killer":"Red_TwinBlast","killed":"Blue_Kallari","timestamp":1015803},{"killer":"Red_TwinBlast","killed":"Blue_Muriel","timestamp":1045948},{"killer":"Red_Sparrow","killed":"Blue_Gadget","timestamp":1046984},{"killer":"jcalvin95","killed":"Blue_Howitzer","timestamp":1057325},{"killer":"jcalvin95","killed":"Blue_Steel","timestamp":1079995},{"killer":"jcalvin95","killed":"Blue_Muriel","timestamp":1123263},{"killer":"Red_Murdock","killed":"Blue_Steel","timestamp":1167859},{"killer":"Red_Sparrow","killed":"Blue_Gadget","timestamp":1220471},{"killer":"Red_Murdock","killed":"Blue_Howitzer","timestamp":1244539},{"killer":"Red_Murdock","killed":"Blue_Steel","timestamp":1250830},{"killer":"Red_TwinBlast","killed":"Blue_Muriel","timestamp":1315978},{"killer":"Red_Sparrow","killed":"Blue_Kallari","timestamp":1335317},{"killer":"Red_Murdock","killed":"Blue_Gadget","timestamp":1335885},{"killer":"jcalvin95","killed":"Blue_Howitzer","timestamp":1344786},{"killer":"Red_Murdock","killed":"Blue_Muriel","timestamp":1389805},{"killer":"Red_TwinBlast","killed":"Blue_Steel","timestamp":1411387},{"killer":"jcalvin95","killed":"Blue_Gadget","timestamp":1413628},{"killer":"jcalvin95","killed":"Blue_Howitzer","timestamp":1415636},{"killer":"Red_TwinBlast","killed":"Blue_Kallari","timestamp":1443356},{"killer":"Blue_Steel","killed":"Red_Rampage","timestamp":1468250},{"killer":"jcalvin95","killed":"Blue_Steel","timestamp":1489520},{"killer":"jcalvin95","killed":"Blue_Howitzer","timestamp":1491025},{"killer":"Red_Murdock","killed":"Blue_Muriel","timestamp":1492396},{"killer":"Red_Sparrow","killed":"Blue_Kallari","timestamp":1522811},{"killer":"Blue_Muriel","killed":"jcalvin95","timestamp":1549998},{"killer":"Red_Murdock","killed":"Blue_Steel","timestamp":1566497},{"killer":"Red_TwinBlast","killed":"Blue_Muriel","timestamp":1588880},{"killer":"Red_Sparrow","killed":"Blue_Kallari","timestamp":1595739},{"killer":"Red_Murdock","killed":"Blue_Howitzer","timestamp":1601646},{"killer":"Red_Rampage","killed":"Blue_Gadget","timestamp":1615131},{"killer":"Red_Murdock","killed":"Blue_Steel","timestamp":1645046},{"killer":"Red_Sparrow","killed":"Blue_Muriel","timestamp":1669624},{"killer":"Blue_Howitzer","killed":"Red_TwinBlast","timestamp":1674041},{"killer":"jcalvin95","killed":"Blue_Kallari","timestamp":1688159},{"killer":"Red_Sparrow","killed":"Blue_Steel","timestamp":1716535},{"killer":"Red_Sparrow","killed":"Blue_Howitzer","timestamp":1726262},{"killer":"jcalvin95","killed":"Blue_Gadget","timestamp":1742229},{"killer":"Red_Sparrow","killed":"Blue_Muriel","timestamp":1754729},{"killer":"jcalvin95","killed":"Blue_Steel","timestamp":1797115},{"killer":"jcalvin95","killed":"Blue_Howitzer","timestamp":1808572},{"killer":"Red_Sparrow","killed":"Blue_Kallari","timestamp":1817205},{"killer":"Red_Sparrow","killed":"Blue_Gadget","timestamp":1827984},{"killer":"Red_Murdock","killed":"Blue_Muriel","timestamp":1832234},{"killer":"Red_Sparrow","killed":"Blue_Steel","timestamp":1871312},{"killer":"Red_Murdock","killed":"Blue_Howitzer","timestamp":1892355},{"killer":"Red_Sparrow","killed":"Blue_Kallari","timestamp":1896973},{"killer":"jcalvin95","killed":"Blue_Muriel","timestamp":1909240},{"killer":"Red_TwinBlast","killed":"Blue_Steel","timestamp":1939030},{"killer":"Red_TwinBlast","killed":"Blue_Kallari","timestamp":1964080},{"killer":"Red_TwinBlast","killed":"Blue_Howitzer","timestamp":1983907},{"killer":"Blue_Gadget","killed":"Red_Rampage","timestamp":1984108},{"killer":"jcalvin95","killed":"Blue_Muriel","timestamp":1995249},{"killer":"jcalvin95","killed":"Blue_Steel","timestamp":2002177},{"killer":"jcalvin95","killed":"Blue_Kallari","timestamp":2031365},{"killer":"Blue_Steel","killed":"Red_TwinBlast","timestamp":2067010},{"killer":"jcalvin95","killed":"Blue_Steel","timestamp":2070959},{"killer":"jcalvin95","killed":"Blue_Gadget","timestamp":2073977},{"killer":"jcalvin95","killed":"Blue_Howitzer","timestamp":2082772},{"killer":"Blue_Muriel","killed":"jcalvin95","timestamp":2093112},{"killer":"Red_Sparrow","killed":"Blue_Kallari","timestamp":2093246}],"towerKills":[{"killer":"jcalvin95","timestamp":1288891},{"killer":"jcalvin95","timestamp":1965856}],"winningTeam":0}