{"replayId":"ba29be4b47494087b84a79f30fb50bf1","startedAt":"2016-08-02T23:00:02.176Z","lastCheckpointTime":3781004,"newCheckpointTime":3841009,"isLive":false,"gameType":"SOLO AI","players":[{"team":0,"hero":"HeroData_Venus","username":"trinaself68","accountId":"68ccca85054147bb91be69fa95441190","damageToTowers":1666,"damageToHeroes":35355,"damageToJungle":0,"damageToMinions":196339,"damageToHarvesters":7344,"damageToInhibitors":12297,"heroLevel":15,"deaths":6,"assists":3,"towerLastHits":0,"mmr":null,"kills":12},{"team":0,"hero":"HeroData_Price","username":"Red_Murdock","accountId":"bot","damageToTowers":0,"damageToHeroes":0,"damageToJungle":0,"damageToMinions":0,"damageToHarvesters":0,"damageToInhibitors":0,"heroLevel":15,"deaths":2,"assists":10,"towerLastHits":1,"mmr":null,"kills":4},{"team":0,"hero":"HeroData_Totem","username":"Red_Dekker","accountId":"bot","damageToTowers":0,"damageToHeroes":0,"damageToJungle":0,"damageToMinions":0,"damageToHarvesters":0,"damageToInhibitors":0,"heroLevel":15,"deaths":3,"assists":9,"towerLastHits":1,"mmr":null,"kills":3},{"team":0,"hero":"HeroData_ArcBlade","username":"Red_Feng Mao","accountId":"bot","damageToTowers":0,"damageToHeroes":0,"damageToJungle":0,"damageToMinions":0,"damageToHarvesters":0,"damageToInhibitors":0,"heroLevel":15,"deaths":3,"assists":3,"towerLastHits":0,"mmr":null,"kills":6},{"team":0,"hero":"HeroData_Chains","username":"Red_Riktor","accountId":"bot","damageToTowers":0,"damageToHeroes":0,"damageToJungle":0,"damageToMinions":0,"damageToHarvesters":0,"damageToInhibitors":0,"heroLevel":15,"deaths":5,"assists":5,"towerLastHits":0,"mmr":null,"kills":4},{"team":1,"hero":"HeroData_HyperBreach","username":"Blue_Howitzer","accountId":"bot","damageToTowers":0,"damageToHeroes":0,"damageToJungle":0,"damageToMinions":0,"damageToHarvesters":0,"damageToInhibitors":0,"heroLevel":15,"deaths":11,"assists":3,"towerLastHits":0,"mmr":null,"kills":5},{"team":1,"hero":"HeroData_Coil","username":"Blue_GRIM.exe","accountId":"bot","damageToTowers":0,"damageToHeroes":0,"damageToJungle":0,"damageToMinions":0,"damageToHarvesters":0,"damageToInhibitors":0,"heroLevel":15,"deaths":3,"assists":8,"towerLastHits":0,"mmr":null,"kills":2},{"team":1,"hero":"HeroData_Muriel","username":"Blue_Muriel","accountId":"bot","damageToTowers":0,"damageToHeroes":0,"damageToJungle":0,"damageToMinions":0,"damageToHarvesters":0,"damageToInhibitors":0,"heroLevel":15,"deaths":7,"assists":0,"towerLastHits":0,"mmr":null,"kills":3},{"team":1,"hero":"HeroData_Steel","username":"Blue_Steel","accountId":"bot","damageToTowers":0,"damageToHeroes":0,"damageToJungle":0,"damageToMinions":0,"damageToHarvesters":0,"damageToInhibitors":0,"heroLevel":14,"deaths":11,"assists":2,"towerLastHits":0,"mmr":null,"kills":5},{"team":1,"hero":"HeroData_Kurohane","username":"Blue_Kallari","accountId":"bot","damageToTowers":0,"damageToHeroes":0,"damageToJungle":0,"damageToMinions":0,"damageToHarvesters":0,"damageToInhibitors":0,"heroLevel":15,"deaths":5,"assists":2,"towerLastHits":3,"mmr":null,"kills":7}],"kills":[{"killer":"Red_Riktor","killed":"Blue_Kallari","timestamp":317590},{"killer":"Blue_Muriel","killed":"Red_Murdock","timestamp":476490},{"killer":"Red_Riktor","killed":"Blue_Steel","timestamp":585948},{"killer":"trinaself68","killed":"Blue_GRIM.exe","timestamp":649774},{"killer":"Red_Riktor","killed":"Blue_Steel","timestamp":650343},{"killer":"Blue_Muriel","killed":"Red_Murdock","timestamp":660274},{"killer":"Red_Murdock","killed":"Blue_Howitzer","timestamp":907572},{"killer":"Blue_Steel","killed":"trinaself68","timestamp":1087385},{"killer":"Red_Dekker","killed":"Blue_GRIM.exe","timestamp":1197208},{"killer":"Blue_Steel","killed":"Red_Feng Mao","timestamp":1333967},{"killer":"Blue_Howitzer","killed":"Red_Riktor","timestamp":1369521},{"killer":"Red_Murdock","killed":"Blue_Kallari","timestamp":1413607},{"killer":"Red_Dekker","killed":"Blue_GRIM.exe","timestamp":1429787},{"killer":"Red_Murdock","killed":"Blue_Kallari","timestamp":1561001},{"killer":"Blue_Howitzer","killed":"trinaself68","timestamp":1571746},{"killer":"Red_Feng Mao","killed":"Blue_Muriel","timestamp":1687065},{"killer":"Red_Riktor","killed":"Blue_Kallari","timestamp":1727537},{"killer":"Blue_Howitzer","killed":"Red_Riktor","timestamp":1830936},{"killer":"trinaself68","killed":"Blue_Steel","timestamp":1987907},{"killer":"Blue_Howitzer","killed":"trinaself68","timestamp":2070265},{"killer":"Blue_Steel","killed":"Red_Dekker","timestamp":2080636},{"killer":"Blue_Kallari","killed":"Red_Feng Mao","timestamp":2172750},{"killer":"Red_Murdock","killed":"Blue_GRIM.exe","timestamp":2182623},{"killer":"Red_Murdock","killed":"Blue_Howitzer","timestamp":2361413},{"killer":"Red_Dekker","killed":"Blue_Kallari","timestamp":2381706},{"killer":"Blue_GRIM.exe","killed":"Red_Murdock","timestamp":2480653},{"killer":"Red_Feng Mao","killed":"Blue_GRIM.exe","timestamp":2613848},{"killer":"trinaself68","killed":"Blue_Howitzer","timestamp":2614049},{"killer":"trinaself68","killed":"Blue_Steel","timestamp":2572399},{"killer":"Red_Feng Mao","killed":"Blue_GRIM.exe","timestamp":2613848},{"killer":"trinaself68","killed":"Blue_Howitzer","timestamp":2614049},{"killer":"Blue_Kallari","killed":"Red_Riktor","timestamp":3088187},{"killer":"Red_Murdock","killed":"Blue_Kallari","timestamp":3089726},{"killer":"Red_Murdock","killed":"Blue_Howitzer","timestamp":3000901},{"killer":"Red_Murdock","killed":"Blue_Howitzer","timestamp":3000901},{"killer":"Red_Murdock","killed":"Blue_Howitzer","timestamp":3000901},{"killer":"Red_Riktor","killed":"Blue_Kallari","timestamp":2957617},{"killer":"trinaself68","killed":"Blue_Muriel","timestamp":2957817},{"killer":"Blue_GRIM.exe","killed":"Red_Feng Mao","timestamp":2968120},{"killer":"Red_Murdock","killed":"Blue_Howitzer","timestamp":3000901},{"killer":"Red_Murdock","killed":"Blue_Howitzer","timestamp":3000901},{"killer":"Blue_Kallari","killed":"Red_Riktor","timestamp":3088187},{"killer":"Red_Murdock","killed":"Blue_Kallari","timestamp":3089726},{"killer":"Blue_GRIM.exe","killed":"trinaself68","timestamp":3144038},{"killer":"Blue_GRIM.exe","killed":"trinaself68","timestamp":3144038},{"killer":"Blue_Kallari","killed":"Red_Dekker","timestamp":3316938},{"killer":"trinaself68","killed":"Blue_Steel","timestamp":3337209},{"killer":"Red_Murdock","killed":"Blue_GRIM.exe","timestamp":3340187},{"killer":"Red_Murdock","killed":"Blue_Kallari","timestamp":3405045},{"killer":"Blue_GRIM.exe","killed":"trinaself68","timestamp":3457162},{"killer":"Red_Murdock","killed":"Blue_Kallari","timestamp":3693697},{"killer":"Red_Murdock","killed":"Blue_Steel","timestamp":3760824},{"killer":"Red_Murdock","killed":"Blue_GRIM.exe","timestamp":3774180},{"killer":"Red_Murdock","killed":"Blue_Kallari","timestamp":3693697},{"killer":"Red_Murdock","killed":"Blue_Kallari","timestamp":3693697},{"killer":"Red_Murdock","killed":"Blue_Kallari","timestamp":3693697},{"killer":"Blue_Kallari","killed":"Red_Murdock","timestamp":3795750},{"killer":"Blue_Kallari","killed":"Red_Murdock","timestamp":3795750},{"killer":"Blue_Kallari","killed":"Red_Murdock","timestamp":3795750},{"killer":"Blue_Kallari","killed":"Red_Murdock","timestamp":3795750}],"towerKills":[{"killer":"trinaself68","timestamp":1722685},{"killer":"trinaself68","timestamp":2451208},{"killer":"trinaself68","timestamp":2890773},{"killer":"trinaself68","timestamp":3725833}],"winningTeam":0}