{"replayId":"cf0b1efb0dc64536bc90ee66b849d59f","startedAt":"2016-08-04T15:48:12.907Z","lastCheckpointTime":1140316,"newCheckpointTime":1200337,"isLive":false,"gameType":"PVP","players":[{"team":0,"hero":"HeroData_Pyro","username":"Gustavocarcara1","accountId":"cc73d10b91444b529b9f8b19ef31f875","damageToTowers":486,"damageToHeroes":6832,"damageToJungle":4382,"damageToMinions":24253,"damageToHarvesters":2272,"damageToInhibitors":0,"heroLevel":12,"deaths":0,"assists":7,"towerLastHits":0,"mmr":null,"kills":4},{"team":1,"hero":"HeroData_RiftMage","username":"orfarkas","accountId":"be20b91daf644a33944b42f5aec81882","damageToTowers":0,"damageToHeroes":1455,"damageToJungle":0,"damageToMinions":851,"damageToHarvesters":0,"damageToInhibitors":0,"heroLevel":6,"deaths":10,"assists":2,"towerLastHits":0,"mmr":null,"kills":0},{"team":0,"hero":"HeroData_Tomahawk","username":"ItCaptainObvious","accountId":"6af4f6b4ab3b43c487f3019267f8ec80","damageToTowers":397,"damageToHeroes":8801,"damageToJungle":12238,"damageToMinions":6611,"damageToHarvesters":0,"damageToInhibitors":0,"heroLevel":11,"deaths":2,"assists":4,"towerLastHits":2,"mmr":null,"kills":10},{"team":1,"hero":"HeroData_Grux","username":"gurybio7","accountId":"a1a5b45261d14ae08d16fdbe593b6c66","damageToTowers":556,"damageToHeroes":4474,"damageToJungle":9704,"damageToMinions":6853,"damageToHarvesters":0,"damageToInhibitors":0,"heroLevel":10,"deaths":6,"assists":1,"towerLastHits":0,"mmr":null,"kills":4},{"team":0,"hero":"HeroData_Grux","username":"IceSkull29","accountId":"72e89ada8845407d91c60016e0ef0120","damageToTowers":58,"damageToHeroes":2481,"damageToJungle":6901,"damageToMinions":27482,"damageToHarvesters":0,"damageToInhibitors":0,"heroLevel":11,"deaths":0,"assists":2,"towerLastHits":0,"mmr":null,"kills":1},{"team":0,"hero":"HeroData_Chains","username":"FatCatInCadilac","accountId":"b5097fea49514eaaa883bc89dd749ce0","damageToTowers":959,"damageToHeroes":8307,"damageToJungle":2642,"damageToMinions":17938,"damageToHarvesters":0,"damageToInhibitors":0,"heroLevel":11,"deaths":1,"assists":6,"towerLastHits":2,"mmr":null,"kills":7},{"team":1,"hero":"HeroData_TwinBlast","username":"cambeeng","accountId":"5438fa4ec72d4768a248c5067db689fd","damageToTowers":0,"damageToHeroes":3689,"damageToJungle":1358,"damageToMinions":15096,"damageToHarvesters":0,"damageToInhibitors":0,"heroLevel":11,"deaths":0,"assists":2,"towerLastHits":0,"mmr":null,"kills":1},{"team":1,"hero":"HeroData_Pyro","username":"TheRedResinXx","accountId":"6b385b3a406040a6af7a853db7635881","damageToTowers":13,"damageToHeroes":7715,"damageToJungle":18328,"damageToMinions":15357,"damageToHarvesters":0,"damageToInhibitors":0,"heroLevel":12,"deaths":7,"assists":2,"towerLastHits":0,"mmr":null,"kills":2},{"team":0,"hero":"HeroData_ArcBlade","username":"darkdestroyermb","accountId":"47a43a3201be408ab08a0c8d4644db07","damageToTowers":1004,"damageToHeroes":4637,"damageToJungle":0,"damageToMinions":18995,"damageToHarvesters":0,"damageToInhibitors":0,"heroLevel":10,"deaths":5,"assists":7,"towerLastHits":0,"mmr":null,"kills":6},{"team":1,"hero":"HeroData_Steel","username":"Arcticbeast","accountId":"33c2c2d1cbf7455e997c8abe603ee75e","damageToTowers":0,"damageToHeroes":3328,"damageToJungle":0,"damageToMinions":7279,"damageToHarvesters":0,"damageToInhibitors":0,"heroLevel":9,"deaths":5,"assists":1,"towerLastHits":0,"mmr":null,"kills":1}],"kills":[{"killer":"darkdestroyermb","killed":"orfarkas","timestamp":70063},{"killer":"darkdestroyermb","killed":"TheRedResinXx","timestamp":88809},{"killer":"darkdestroyermb","killed":"orfarkas","timestamp":139927},{"killer":"TheRedResinXx","killed":"darkdestroyermb","timestamp":145924},{"killer":"ItCaptainObvious","killed":"Arcticbeast","timestamp":154929},{"killer":"FatCatInCadilac","killed":"TheRedResinXx","timestamp":219940},{"killer":"ItCaptainObvious","killed":"gurybio7","timestamp":309286},{"killer":"FatCatInCadilac","killed":"TheRedResinXx","timestamp":332593},{"killer":"gurybio7","killed":"darkdestroyermb","timestamp":376278},{"killer":"FatCatInCadilac","killed":"orfarkas","timestamp":381648},{"killer":"ItCaptainObvious","killed":"TheRedResinXx","timestamp":451807},{"killer":"ItCaptainObvious","killed":"orfarkas","timestamp":459553},{"killer":"Gustavocarcara1","killed":"Arcticbeast","timestamp":466253},{"killer":"Gustavocarcara1","killed":"orfarkas","timestamp":534069},{"killer":"ItCaptainObvious","killed":"gurybio7","timestamp":595731},{"killer":"ItCaptainObvious","killed":"Arcticbeast","timestamp":600768},{"killer":"ItCaptainObvious","killed":"orfarkas","timestamp":612800},{"killer":"gurybio7","killed":"darkdestroyermb","timestamp":704033},{"killer":"FatCatInCadilac","killed":"TheRedResinXx","timestamp":714242},{"killer":"Gustavocarcara1","killed":"Arcticbeast","timestamp":719064},{"killer":"FatCatInCadilac","killed":"gurybio7","timestamp":725599},{"killer":"FatCatInCadilac","killed":"orfarkas","timestamp":786391},{"killer":"darkdestroyermb","killed":"TheRedResinXx","timestamp":811323},{"killer":"ItCaptainObvious","killed":"gurybio7","timestamp":823543},{"killer":"Gustavocarcara1","killed":"Arcticbeast","timestamp":830672},{"killer":"FatCatInCadilac","killed":"orfarkas","timestamp":897984},{"killer":"TheRedResinXx","killed":"darkdestroyermb","timestamp":920998},{"killer":"Arcticbeast","killed":"ItCaptainObvious","timestamp":938295},{"killer":"darkdestroyermb","killed":"TheRedResinXx","timestamp":997371},{"killer":"IceSkull29","killed":"orfarkas","timestamp":1046346},{"killer":"ItCaptainObvious","killed":"gurybio7","timestamp":1051831},{"killer":"gurybio7","killed":"ItCaptainObvious","timestamp":1052739},{"killer":"cambeeng","killed":"darkdestroyermb","timestamp":1078860},{"killer":"ItCaptainObvious","killed":"orfarkas","timestamp":1161846},{"killer":"darkdestroyermb","killed":"gurybio7","timestamp":1173896}],"towerKills":[{"killer":"ItCaptainObvious","timestamp":751736},{"killer":"FatCatInCadilac","timestamp":1012328},{"killer":"FatCatInCadilac","timestamp":1176113}],"winningTeam":0}